{
    "pt-br": {
        "menu": [
            {
                "name": "Sobre",
                "url": "/"
            },
            {
                "name": "Experiência",
                "url": "#",
                "items": [
                    {
                        "name": "Engenheiro de software",
                        "url": "/experiencia/engenheiro-de-software"
                    },
                    {
                        "name": "Instrutor",
                        "url": "/experiencia/instrutor"
                    },
                    {
                        "name": "Palestras",
                        "url": "/experiencia/palestras"
                    },
                    {
                        "name": "Product Owner",
                        "url": "/experiencia/product-owner"
                    },
                    {
                        "name": "Facilitador",
                        "url": "/experiencia/facilitador"
                    }
                ]
            },
            {
                "name": "Currículum Vitae",
                "url": "/curriculum-vitae"
            }
        ],
        "home": {
            "welcome": "Olá!",
            "subdescription": "Meu nome é Carlos Henrique.",
            "shortDescription": "<strong>Sou engenheiro de software, product owner, instrutor e facilitador no UOL.</strong>",
            "description": [
                "Pós-graduado em Gestão em Tecnologia da Informação, escrevi um  <a href=\"TROCAR\">artigo</a>. Como engenheiro de software, alguns de meus trabalhos podem ser vistos <a href=\"TROCAR\">aqui</a> ou no <a href=\"https://github.com/carlohcs\">GitHub</a>.",
                "Ultimamente tenho me aventurado a escrever no <a href=\"https://medium.com/@carlohcs\">Medium</a> e a <a href=\"TROCAR\">palestrar</a>.",
                "Acredito que todo mundo deve ter uma <a href=\"https://missaopessoal.com.br\">missão pessoal</a> na vida."
            ],
            "connect": "Conecte-se:"
        }
    },
    "en": {
        "menu": [
            {
                "name": "About",
                "url": "/en"
            },
            {
                "name": "Experience",
                "url": "#",
                "items": [
                    {
                        "name": "Software Engineer",
                        "url": "/en/experience/software-engineer"
                    },
                    {
                        "name": "Instructor",
                        "url": "/en/experience/instructor"
                    },
                    {
                        "name": "Talks",
                        "url": "/en/experience/talks"
                    },
                    {
                        "name": "Product Owner",
                        "url": "/en/experience/product-owner"
                    },
                    {
                        "name": "Facilitator",
                        "url": "/en/experience/facilitator"
                    }
                ]
            },
            {
                "name": "Resume",
                "url": "/en/resume"
            }
        ],
        "home": {
            "welcome": "Hello!",
            "subdescription": "My name is Carlos Henrique.",
            "shortDescription": "<strong>I'm a software engineer, product owner, instructor, and facilitator at UOL.</strong>",
            "description": [
                "Recently graduated as a IT Management Specialist I wrote a <a href=\"TROCAR\"> article </a>. As a software engineer, some of my work can be viewed <a href=\"TROCAR\"> here </a> or <a href=\"https://github.com/carlohcs\"> GitHub </a>. ",
                "Lately I've been venturing to write at the <a href=\"https://medium.com/@carlohcs\"> Medium </a>. Check out some <a href=\"TROCAR\"> lectures I gave </a>.",
                "I believe everyone should have a personal mission in life. Don't you know what it is or how to do it? <a href=\"https://missaopessoal.com.br\"> Do your mission</a>."
            ],
            "connect": "Connect:"
        }
    }
}